ramifi/__init__.py
ramifi/ncbi_trace_lineage_to_json.py
ramifi/ramifi.py
ramifi/translate.py
ramifi/varJSonToGFF.py
ramifi/data/NC_045512.fasta
ramifi/data/NC_045512.fasta.fai
ramifi/data/Omicron_lineage_vs_allOthersInOmicron.gff
ramifi/data/Omicron_lineage_vs_allOthersInOmicron.json
ramifi/data/SARS-CoV-2.json
ramifi/data/__init__.py
ramifi/data/lineage_mutation.json
ramifi/data/uniq_variants.json
ramifi/data/variant_mutation.gff
ramifi/data/variant_mutation.json
ramifi-0.3.0.dist-info/LICENSE
ramifi-0.3.0.dist-info/METADATA
ramifi-0.3.0.dist-info/WHEEL
ramifi-0.3.0.dist-info/entry_points.txt
ramifi-0.3.0.dist-info/top_level.txt
ramifi-0.3.0.dist-info/RECORD
