Metadata-Version: 2.1
Name: ramifi
Version: 0.3.0
Summary: Script to do recombinant read analysis
Home-page: https://github.com/chienchi/ramifi
Author: Chienchi Lo
Author-email: chienchi@lanl.gov
License: LICENSE
Keywords: recombinant,mix-infection
Platform: UNKNOWN
Classifier: Programming Language :: Python :: 3
Classifier: License :: OSI Approved :: GNU General Public License v3 (GPLv3)
Classifier: Intended Audience :: Science/Research
Classifier: Topic :: Scientific/Engineering :: Bio-Informatics
Classifier: Operating System :: OS Independent
Classifier: Development Status :: 4 - Beta
Requires-Dist: plotly (>=5.5.0)
Requires-Dist: pandas (>=1.2.4)
Requires-Dist: pysam (>=0.16.0.1)
Requires-Dist: kaleido (>=0.2.1)
Requires-Dist: biopython (==1.78)
Requires-Dist: importlib-resources (==5.7.1)
